{
  "Stages": [
    {
      "Milestones": [
        null,
        null,
        null,
        null,
        null,
        null,
        null,
        {
          "Amount": 0,
          "Encryption": {
            "IsEncrypted": true,
            "TitleUpper": "^UI_EXPED_PIRATE_MAP1_SUB_CRYPT",
            "Subtitle": "^UI_EXPED_SAVE_FREIGHT_S_CRYPT",
            "Description": "^UI_EXPED_PIRATE_MAP2_SUB_CRYPT",
            "Patch": {
              "Filename": "textures/ui/frontend/icons/expedition/encrypted.patch.3.dds"
            },
            "HoverPopupIcon": {
              "Filename": "textures/ui/frontend/icons/missions/expeditionmissions/mission.atlas.on.dds"
            },
            "DecryptMissionId": "^PARTY_PLANET1",
            "DecryptMissionSeed": 6
          }
        }
      ]
    },
    {
      "Milestones": [
        null,
        null,
        null,
        null,
        null,
        null,
        null,
        {
          "Amount": 0,
          "Encryption": {
            "IsEncrypted": true,
            "TitleUpper": "^UI_EXPED_PIRATE_MAP1_SUB_CRYPT",
            "Subtitle": "^UI_EXPED_SAVE_FREIGHT_S_CRYPT",
            "Description": "^UI_EXPED_PIRATE_MAP2_SUB_CRYPT",
            "Patch": {
              "Filename": "textures/ui/frontend/icons/expedition/encrypted.patch.3.dds"
            },
            "HoverPopupIcon": {
              "Filename": "textures/ui/frontend/icons/missions/expeditionmissions/mission.atlas.on.dds"
            },
            "DecryptMissionId": "^PARTY_PLANET2",
            "DecryptMissionSeed": 16
          }
        }
      ]
    },
    {
      "Milestones": [
        null,
        null,
        null,
        null,
        null,
        null,
        null,
        {
          "Amount": 0,
          "Encryption": {
            "IsEncrypted": true,
            "TitleUpper": "^UI_EXPED_PIRATE_MAP1_SUB_CRYPT",
            "Subtitle": "^UI_EXPED_SAVE_FREIGHT_S_CRYPT",
            "Description": "^UI_EXPED_PIRATE_MAP2_SUB_CRYPT",
            "Patch": {
              "Filename": "textures/ui/frontend/icons/expedition/encrypted.patch.3.dds"
            },
            "HoverPopupIcon": {
              "Filename": "textures/ui/frontend/icons/missions/expeditionmissions/mission.atlas.on.dds"
            },
            "DecryptMissionId": "^PARTY_PLANET3",
            "DecryptMissionSeed": 26
          }
        }
      ]
    },
    {
      "Milestones": [
        null,
        null,
        null,
        null,
        null,
        null,
        null,
        {
          "Amount": 0,
          "Encryption": {
            "IsEncrypted": true,
            "TitleUpper": "^UI_EXPED_PIRATE_MAP1_SUB_CRYPT",
            "Subtitle": "^UI_EXPED_SAVE_FREIGHT_S_CRYPT",
            "Description": "^UI_EXPED_PIRATE_MAP2_SUB_CRYPT",
            "Patch": {
              "Filename": "textures/ui/frontend/icons/expedition/encrypted.patch.3.dds"
            },
            "HoverPopupIcon": {
              "Filename": "textures/ui/frontend/icons/missions/expeditionmissions/mission.atlas.on.dds"
            },
            "DecryptMissionId": "^PARTY_PLANET4",
            "DecryptMissionSeed": 36
          }
        }
      ]
    },
    {
      "Milestones": [
        null,
        null,
        null,
        null,
        null,
        null,
        null,
        {
          "Amount": 0,
          "Encryption": {
            "IsEncrypted": true,
            "TitleUpper": "^UI_EXPED_PIRATE_MAP1_SUB_CRYPT",
            "Subtitle": "^UI_EXPED_SAVE_FREIGHT_S_CRYPT",
            "Description": "^UI_EXPED_PIRATE_MAP2_SUB_CRYPT",
            "Patch": {
              "Filename": "textures/ui/frontend/icons/expedition/encrypted.patch.3.dds"
            },
            "HoverPopupIcon": {
              "Filename": "textures/ui/frontend/icons/missions/expeditionmissions/mission.atlas.on.dds"
            },
            "DecryptMissionId": "^PARTY_PLANET5",
            "DecryptMissionSeed": 46
          }
        }
      ]
    }
  ]
}